instamojo_wrapper/__init__.py
instamojo_wrapper/api.py
instamojo_wrapper-1.2.0.dist-info/LICENSE
instamojo_wrapper-1.2.0.dist-info/METADATA
instamojo_wrapper-1.2.0.dist-info/WHEEL
instamojo_wrapper-1.2.0.dist-info/top_level.txt
instamojo_wrapper-1.2.0.dist-info/RECORD
