Metadata-Version: 1.1
Name: instamojo_wrapper
Version: 1.2.0
Summary: Instamojo API 1.1 Wrapper
Home-page: http://github.com/Instamojo/instamojo-py
Author: Instamojo Developers
Author-email: support@instamojo.com
License: MIT
Keywords: instamojo,api,wrapper,1.1
Platform: UNKNOWN
Classifier: Development Status :: 4 - Beta
Classifier: Intended Audience :: Developers
Classifier: Natural Language :: English
Classifier: License :: OSI Approved :: MIT License
Classifier: Operating System :: OS Independent
Classifier: Programming Language :: Python
Classifier: Programming Language :: Python :: 2.7
Classifier: Programming Language :: Python :: 3.2
Classifier: Programming Language :: Python :: 3.3
Classifier: Programming Language :: Python :: 3.4
Classifier: Programming Language :: Python :: 3.5
Classifier: Topic :: Software Development :: Libraries :: Python Modules
